nep_aldebaran/Audio.py
nep_aldebaran/AutonomusLife.py
nep_aldebaran/BehaviorManager.py
nep_aldebaran/BodyMove.py
nep_aldebaran/Bumpers.py
nep_aldebaran/Leds.py
nep_aldebaran/PeoplePerception.py
nep_aldebaran/SayText.py
nep_aldebaran/SensorEvents.py
nep_aldebaran/Sonars.py
nep_aldebaran/SpeechRecognition.py
nep_aldebaran/Tablet.py
nep_aldebaran/Touch.py
nep_aldebaran/Tracking.py
nep_aldebaran/Volume.py
nep_aldebaran/__init__.py
nepsy/__init__.py
nepsy/version.py
nepsy-0.1.5.0.dist-info/LICENSE
nepsy-0.1.5.0.dist-info/METADATA
nepsy-0.1.5.0.dist-info/WHEEL
nepsy-0.1.5.0.dist-info/top_level.txt
nepsy-0.1.5.0.dist-info/RECORD
